kitinv1.py
kitinv1-0.0.1.dist-info/LICENSES/neutral/_Default/Professional/de-license.rtf
kitinv1-0.0.1.dist-info/LICENSES/neutral/Volume/Professional/license.rtf
kitinv1-0.0.1.dist-info/license.rtf
kitinv1-0.0.1.dist-info/LICENSES/neutral/OEM/Professional/license.rtf
kitinv1-0.0.1.dist-info/LICENSES/neutral/_Default/Professional/license.rtf
kitinv1-0.0.1.dist-info/LICENSES/neutral/OEM/Professional/de-license.rtf
kitinv1-0.0.1.dist-info/WHEEL
kitinv1-0.0.1.dist-info/METADATA
kitinv1-0.0.1.dist-info/RECORD
